ncm/__init__.py
ncm/client.py
ncm/entities.py
ncm/exceptions.py
siscomex_ncm-1.0.2.dist-info/LICENSE
siscomex_ncm-1.0.2.dist-info/METADATA
siscomex_ncm-1.0.2.dist-info/WHEEL
siscomex_ncm-1.0.2.dist-info/RECORD
