Metadata-Version: 2.3
Name: siscomex-ncm
Version: 1.0.2
Summary: API access to the NCM (Nomenclatura Comum do Mercosul) by Siscomex
License: MIT
Author: Leonardo Gregianin
Author-email: leogregianin@gmail.com
Requires-Python: >=3.8,<4.0
Classifier: License :: OSI Approved :: MIT License
Classifier: Programming Language :: Python :: 3
Classifier: Programming Language :: Python :: 3.8
Classifier: Programming Language :: Python :: 3.9
Classifier: Programming Language :: Python :: 3.10
Classifier: Programming Language :: Python :: 3.11
Classifier: Programming Language :: Python :: 3.12
Classifier: Programming Language :: Python :: 3.13
Requires-Dist: urllib3 (>=1.26.9,<2.0.0)
Project-URL: Repository, https://github.com/leogregianin/siscomex-ncm
